lopaths/__init__.py
lopaths/_setup_graph.py
lopaths/_test_routes.py
lopaths/graph.py
lopaths/graph_utils.cp38-win_amd64.pyd
lopaths/graph_utils.pxd
lopaths/graph_utils.pyx
lopaths/sig_fig_rounding.py
lopaths/test_graph.py
lopaths/test_routes.py
lopaths-0.9.0a7.dist-info/LICENSE
lopaths-0.9.0a7.dist-info/METADATA
lopaths-0.9.0a7.dist-info/WHEEL
lopaths-0.9.0a7.dist-info/top_level.txt
lopaths-0.9.0a7.dist-info/RECORD
