Metadata-Version: 2.1
Name: lopaths
Version: 0.9.0a7
Summary: Package to find locally optimal routes in route networks
Home-page: https://github.com/vemomoto/vemomoto
Author: Samuel M. Fischer
License: LGPLv3
Project-URL: Bug Tracker, https://github.com/vemomoto/vemomoto/issues
Project-URL: Documentation, https://vemomoto.github.io/lopaths
Project-URL: Source Code, https://github.com/vemomoto/vemomoto/tree/master/lopaths
Project-URL: Publication, https://doi.org/10.1016/j.trb.2020.09.007
Keywords: alternative paths,choice set,local optimality,road network,route choice
Platform: UNKNOWN
Classifier: License :: OSI Approved :: GNU Lesser General Public License v3 (LGPLv3)
Classifier: Development Status :: 3 - Alpha
Classifier: Intended Audience :: Science/Research
Requires-Python: >=3.6
Requires-Dist: numpy
Requires-Dist: sharedmem
Requires-Dist: vemomoto-core-concurrent
Requires-Dist: vemomoto-core-npcollections
Requires-Dist: vemomoto-core-tools (>=0.9.0.a4)
Requires-Dist: cython
